{
  "date": "2026-03-23",
  "fetched_at": "2026-03-24T07:16:18.387Z",
  "total_games": 16,
  "completed_games": 16,
  "games": [
    {
      "espnEventId": "401865060",
      "commence_time": "2026-03-24T01:00Z",
      "home_team": "BYU Cougars",
      "away_team": "Missouri Tigers",
      "home_espnTeamId": "252",
      "away_espnTeamId": "142",
      "completed": true,
      "status": "Final",
      "homeScore": 93,
      "awayScore": 75,
      "actualSpread": -18,
      "winner": "HOME"
    },
    {
      "espnEventId": "401856551",
      "commence_time": "2026-03-23T22:00Z",
      "home_team": "UConn Huskies",
      "away_team": "Syracuse Orange",
      "home_espnTeamId": "41",
      "away_espnTeamId": "183",
      "completed": true,
      "status": "Final",
      "homeScore": 98,
      "awayScore": 45,
      "actualSpread": -53,
      "winner": "HOME"
    },
    {
      "espnEventId": "401856550",
      "commence_time": "2026-03-24T00:00Z",
      "home_team": "South Carolina Gamecocks",
      "away_team": "USC Trojans",
      "home_espnTeamId": "2579",
      "away_espnTeamId": "30",
      "completed": true,
      "status": "Final",
      "homeScore": 101,
      "awayScore": 61,
      "actualSpread": -40,
      "winner": "HOME"
    },
    {
      "espnEventId": "401856555",
      "commence_time": "2026-03-24T02:00Z",
      "home_team": "UCLA Bruins",
      "away_team": "Oklahoma State Cowgirls",
      "home_espnTeamId": "26",
      "away_espnTeamId": "197",
      "completed": true,
      "status": "Final",
      "homeScore": 87,
      "awayScore": 68,
      "actualSpread": -19,
      "winner": "HOME"
    },
    {
      "espnEventId": "401856552",
      "commence_time": "2026-03-23T18:00Z",
      "home_team": "Iowa Hawkeyes",
      "away_team": "Virginia Cavaliers",
      "home_espnTeamId": "2294",
      "away_espnTeamId": "258",
      "completed": true,
      "status": "Final",
      "homeScore": 75,
      "awayScore": 83,
      "actualSpread": 8,
      "winner": "AWAY"
    },
    {
      "espnEventId": "401856554",
      "commence_time": "2026-03-23T23:00Z",
      "home_team": "Vanderbilt Commodores",
      "away_team": "Illinois Fighting Illini",
      "home_espnTeamId": "238",
      "away_espnTeamId": "356",
      "completed": true,
      "status": "Final",
      "homeScore": 75,
      "awayScore": 57,
      "actualSpread": -18,
      "winner": "HOME"
    },
    {
      "espnEventId": "401856549",
      "commence_time": "2026-03-23T16:00Z",
      "home_team": "Louisville Cardinals",
      "away_team": "Alabama Crimson Tide",
      "home_espnTeamId": "97",
      "away_espnTeamId": "333",
      "completed": true,
      "status": "Final",
      "homeScore": 69,
      "awayScore": 68,
      "actualSpread": -1,
      "winner": "HOME"
    },
    {
      "espnEventId": "401856547",
      "commence_time": "2026-03-23T20:00Z",
      "home_team": "Ohio State Buckeyes",
      "away_team": "Notre Dame Fighting Irish",
      "home_espnTeamId": "194",
      "away_espnTeamId": "87",
      "completed": true,
      "status": "Final",
      "homeScore": 73,
      "awayScore": 83,
      "actualSpread": 10,
      "winner": "AWAY"
    },
    {
      "espnEventId": "401856553",
      "commence_time": "2026-03-23T21:00Z",
      "home_team": "West Virginia Mountaineers",
      "away_team": "Kentucky Wildcats",
      "home_espnTeamId": "277",
      "away_espnTeamId": "96",
      "completed": true,
      "status": "Final",
      "homeScore": 73,
      "awayScore": 74,
      "actualSpread": 1,
      "winner": "AWAY"
    },
    {
      "espnEventId": "401865111",
      "commence_time": "2026-03-23T22:00Z",
      "home_team": "Marshall Thundering Herd",
      "away_team": "UMBC Retrievers",
      "home_espnTeamId": "276",
      "away_espnTeamId": "2378",
      "completed": true,
      "status": "Final",
      "homeScore": 66,
      "awayScore": 53,
      "actualSpread": -13,
      "winner": "HOME"
    },
    {
      "espnEventId": "401864990",
      "commence_time": "2026-03-23T22:00Z",
      "home_team": "La Salle Explorers",
      "away_team": "Binghamton Bearcats",
      "home_espnTeamId": "2325",
      "away_espnTeamId": "2066",
      "completed": true,
      "status": "Final",
      "homeScore": 70,
      "awayScore": 61,
      "actualSpread": -9,
      "winner": "HOME"
    },
    {
      "espnEventId": "401865120",
      "commence_time": "2026-03-23T23:00Z",
      "home_team": "Florida Gulf Coast Eagles",
      "away_team": "Loyola Chicago Ramblers",
      "home_espnTeamId": "526",
      "away_espnTeamId": "2350",
      "completed": true,
      "status": "Final",
      "homeScore": 56,
      "awayScore": 62,
      "actualSpread": 6,
      "winner": "AWAY"
    },
    {
      "espnEventId": "401865119",
      "commence_time": "2026-03-23T23:00Z",
      "home_team": "Cleveland State Vikings",
      "away_team": "Monmouth Hawks",
      "home_espnTeamId": "325",
      "away_espnTeamId": "2405",
      "completed": true,
      "status": "Final",
      "homeScore": 74,
      "awayScore": 68,
      "actualSpread": -6,
      "winner": "HOME"
    },
    {
      "espnEventId": "401865113",
      "commence_time": "2026-03-23T23:00Z",
      "home_team": "Southern Indiana Screaming Eagles",
      "away_team": "George Washington Revolutionaries",
      "home_espnTeamId": "88",
      "away_espnTeamId": "45",
      "completed": true,
      "status": "Final",
      "homeScore": 58,
      "awayScore": 61,
      "actualSpread": 3,
      "winner": "AWAY"
    },
    {
      "espnEventId": "401865115",
      "commence_time": "2026-03-23T23:30Z",
      "home_team": "Middle Tennessee Blue Raiders",
      "away_team": "St. Bonaventure Bonnies",
      "home_espnTeamId": "2393",
      "away_espnTeamId": "179",
      "completed": true,
      "status": "Final",
      "homeScore": 69,
      "awayScore": 50,
      "actualSpread": -19,
      "winner": "HOME"
    },
    {
      "espnEventId": "401865123",
      "commence_time": "2026-03-24T00:00Z",
      "home_team": "Arkansas State Red Wolves",
      "away_team": "Radford Highlanders",
      "home_espnTeamId": "2032",
      "away_espnTeamId": "2515",
      "completed": true,
      "status": "Final",
      "homeScore": 83,
      "awayScore": 52,
      "actualSpread": -31,
      "winner": "HOME"
    }
  ]
}
