{
  "date": "2026-03-04",
  "fetched_at": "2026-03-05T07:04:45.584Z",
  "total_games": 41,
  "completed_games": 41,
  "games": [
    {
      "espnEventId": "401851597",
      "commence_time": "2026-03-04T16:00Z",
      "home_team": "Kentucky Wildcats",
      "away_team": "Arkansas Razorbacks",
      "home_espnTeamId": "96",
      "away_espnTeamId": "8",
      "completed": true,
      "status": "Final",
      "homeScore": 94,
      "awayScore": 64,
      "actualSpread": -30,
      "winner": "HOME"
    },
    {
      "espnEventId": "401851184",
      "commence_time": "2026-03-04T16:00Z",
      "home_team": "Miami Hurricanes",
      "away_team": "Stanford Cardinal",
      "home_espnTeamId": "2390",
      "away_espnTeamId": "24",
      "completed": true,
      "status": "Final",
      "homeScore": 83,
      "awayScore": 76,
      "actualSpread": -7,
      "winner": "HOME"
    },
    {
      "espnEventId": "401851278",
      "commence_time": "2026-03-04T17:00Z",
      "home_team": "Kansas State Wildcats",
      "away_team": "Cincinnati Bearcats",
      "home_espnTeamId": "2306",
      "away_espnTeamId": "2132",
      "completed": true,
      "status": "Final",
      "homeScore": 91,
      "awayScore": 66,
      "actualSpread": -25,
      "winner": "HOME"
    },
    {
      "espnEventId": "401851252",
      "commence_time": "2026-03-04T17:00Z",
      "home_team": "Duquesne Dukes",
      "away_team": "VCU Rams",
      "home_espnTeamId": "2184",
      "away_espnTeamId": "2670",
      "completed": true,
      "status": "Final",
      "homeScore": 60,
      "awayScore": 52,
      "actualSpread": -8,
      "winner": "HOME"
    },
    {
      "espnEventId": "401851741",
      "commence_time": "2026-03-04T17:30Z",
      "home_team": "Coastal Carolina Chanticleers",
      "away_team": "South Alabama Jaguars",
      "home_espnTeamId": "324",
      "away_espnTeamId": "6",
      "completed": true,
      "status": "Final",
      "homeScore": 70,
      "awayScore": 80,
      "actualSpread": 10,
      "winner": "AWAY"
    },
    {
      "espnEventId": "401851598",
      "commence_time": "2026-03-04T18:30Z",
      "home_team": "Florida Gators",
      "away_team": "Mississippi State Bulldogs",
      "home_espnTeamId": "57",
      "away_espnTeamId": "344",
      "completed": true,
      "status": "Final",
      "homeScore": 86,
      "awayScore": 68,
      "actualSpread": -18,
      "winner": "HOME"
    },
    {
      "espnEventId": "401851572",
      "commence_time": "2026-03-04T18:30Z",
      "home_team": "Little Rock Trojans",
      "away_team": "Southeast Missouri State Redhawks",
      "home_espnTeamId": "2031",
      "away_espnTeamId": "2546",
      "completed": true,
      "status": "Final",
      "homeScore": 65,
      "awayScore": 68,
      "actualSpread": 3,
      "winner": "AWAY"
    },
    {
      "espnEventId": "401851185",
      "commence_time": "2026-03-04T18:40Z",
      "home_team": "California Golden Bears",
      "away_team": "Wake Forest Demon Deacons",
      "home_espnTeamId": "25",
      "away_espnTeamId": "154",
      "completed": true,
      "status": "Final",
      "homeScore": 75,
      "awayScore": 52,
      "actualSpread": -23,
      "winner": "HOME"
    },
    {
      "espnEventId": "401851279",
      "commence_time": "2026-03-04T19:30Z",
      "home_team": "BYU Cougars",
      "away_team": "Houston Cougars",
      "home_espnTeamId": "252",
      "away_espnTeamId": "248",
      "completed": true,
      "status": "Final",
      "homeScore": 76,
      "awayScore": 66,
      "actualSpread": -10,
      "winner": "HOME"
    },
    {
      "espnEventId": "401851253",
      "commence_time": "2026-03-04T19:30Z",
      "home_team": "Saint Louis Billikens",
      "away_team": "Fordham Rams",
      "home_espnTeamId": "139",
      "away_espnTeamId": "2230",
      "completed": true,
      "status": "Final",
      "homeScore": 68,
      "awayScore": 60,
      "actualSpread": -8,
      "winner": "HOME"
    },
    {
      "espnEventId": "401851742",
      "commence_time": "2026-03-04T20:30Z",
      "home_team": "UL Monroe Warhawks",
      "away_team": "Louisiana Ragin' Cajuns",
      "home_espnTeamId": "2433",
      "away_espnTeamId": "309",
      "completed": true,
      "status": "Final",
      "homeScore": 79,
      "awayScore": 63,
      "actualSpread": -16,
      "winner": "HOME"
    },
    {
      "espnEventId": "401851364",
      "commence_time": "2026-03-04T20:30Z",
      "home_team": "Nebraska Cornhuskers",
      "away_team": "Indiana Hoosiers",
      "home_espnTeamId": "158",
      "away_espnTeamId": "84",
      "completed": true,
      "status": "Final",
      "homeScore": 69,
      "awayScore": 72,
      "actualSpread": 3,
      "winner": "AWAY"
    },
    {
      "espnEventId": "401851573",
      "commence_time": "2026-03-04T21:00Z",
      "home_team": "UT Martin Skyhawks",
      "away_team": "SIU Edwardsville Cougars",
      "home_espnTeamId": "2630",
      "away_espnTeamId": "2565",
      "completed": true,
      "status": "Final",
      "homeScore": 49,
      "awayScore": 63,
      "actualSpread": 14,
      "winner": "AWAY"
    },
    {
      "espnEventId": "401851186",
      "commence_time": "2026-03-04T21:00Z",
      "home_team": "Georgia Tech Yellow Jackets",
      "away_team": "Florida State Seminoles",
      "home_espnTeamId": "59",
      "away_espnTeamId": "52",
      "completed": true,
      "status": "Final",
      "homeScore": 72,
      "awayScore": 60,
      "actualSpread": -12,
      "winner": "HOME"
    },
    {
      "espnEventId": "401851354",
      "commence_time": "2026-03-04T22:00Z",
      "home_team": "South Carolina Upstate Spartans",
      "away_team": "Presbyterian Blue Hose",
      "home_espnTeamId": "2908",
      "away_espnTeamId": "2506",
      "completed": true,
      "status": "Final",
      "homeScore": 60,
      "awayScore": 48,
      "actualSpread": -12,
      "winner": "HOME"
    },
    {
      "espnEventId": "401851724",
      "commence_time": "2026-03-04T22:30Z",
      "home_team": "Omaha Mavericks",
      "away_team": "North Dakota Fighting Hawks",
      "home_espnTeamId": "2437",
      "away_espnTeamId": "155",
      "completed": true,
      "status": "Final",
      "homeScore": 49,
      "awayScore": 39,
      "actualSpread": -10,
      "winner": "HOME"
    },
    {
      "espnEventId": "401851599",
      "commence_time": "2026-03-04T23:00Z",
      "home_team": "Texas A&M Aggies",
      "away_team": "Auburn Tigers",
      "home_espnTeamId": "245",
      "away_espnTeamId": "2",
      "completed": true,
      "status": "Final",
      "homeScore": 49,
      "awayScore": 50,
      "actualSpread": 1,
      "winner": "AWAY"
    },
    {
      "espnEventId": "401851366",
      "commence_time": "2026-03-04T23:00Z",
      "home_team": "Illinois Fighting Illini",
      "away_team": "Wisconsin Badgers",
      "home_espnTeamId": "356",
      "away_espnTeamId": "275",
      "completed": true,
      "status": "Final",
      "homeScore": 82,
      "awayScore": 70,
      "actualSpread": -12,
      "winner": "HOME"
    },
    {
      "espnEventId": "401827882",
      "commence_time": "2026-03-04T23:00Z",
      "home_team": "Lafayette Leopards",
      "away_team": "Colgate Raiders",
      "home_espnTeamId": "322",
      "away_espnTeamId": "2142",
      "completed": true,
      "status": "Final",
      "homeScore": 66,
      "awayScore": 55,
      "actualSpread": -11,
      "winner": "HOME"
    },
    {
      "espnEventId": "401827874",
      "commence_time": "2026-03-04T23:00Z",
      "home_team": "Lehigh Mountain Hawks",
      "away_team": "American University Eagles",
      "home_espnTeamId": "2329",
      "away_espnTeamId": "44",
      "completed": true,
      "status": "Final",
      "homeScore": 60,
      "awayScore": 62,
      "actualSpread": 2,
      "winner": "AWAY"
    },
    {
      "espnEventId": "401823171",
      "commence_time": "2026-03-04T23:00Z",
      "home_team": "Bucknell Bison",
      "away_team": "Army Black Knights",
      "home_espnTeamId": "2083",
      "away_espnTeamId": "349",
      "completed": true,
      "status": "Final",
      "homeScore": 43,
      "awayScore": 56,
      "actualSpread": 13,
      "winner": "AWAY"
    },
    {
      "espnEventId": "401823127",
      "commence_time": "2026-03-04T23:00Z",
      "home_team": "Boston University Terriers",
      "away_team": "Holy Cross Crusaders",
      "home_espnTeamId": "104",
      "away_espnTeamId": "107",
      "completed": true,
      "status": "Final",
      "homeScore": 58,
      "awayScore": 64,
      "actualSpread": 6,
      "winner": "AWAY"
    },
    {
      "espnEventId": "401814679",
      "commence_time": "2026-03-04T23:00Z",
      "home_team": "Akron Zips",
      "away_team": "Massachusetts Minutewomen",
      "home_espnTeamId": "2006",
      "away_espnTeamId": "113",
      "completed": true,
      "status": "Final",
      "homeScore": 64,
      "awayScore": 74,
      "actualSpread": 10,
      "winner": "AWAY"
    },
    {
      "espnEventId": "401851280",
      "commence_time": "2026-03-04T23:30Z",
      "home_team": "Arizona State Sun Devils",
      "away_team": "Arizona Wildcats",
      "home_espnTeamId": "9",
      "away_espnTeamId": "12",
      "completed": true,
      "status": "Final",
      "homeScore": 54,
      "awayScore": 51,
      "actualSpread": -3,
      "winner": "HOME"
    },
    {
      "espnEventId": "401814681",
      "commence_time": "2026-03-04T23:30Z",
      "home_team": "Eastern Michigan Eagles",
      "away_team": "Ohio Bobcats",
      "home_espnTeamId": "2199",
      "away_espnTeamId": "195",
      "completed": true,
      "status": "Final",
      "homeScore": 54,
      "awayScore": 62,
      "actualSpread": 8,
      "winner": "AWAY"
    },
    {
      "espnEventId": "401813219",
      "commence_time": "2026-03-04T23:30Z",
      "home_team": "Central Michigan Chippewas",
      "away_team": "Bowling Green Falcons",
      "home_espnTeamId": "2117",
      "away_espnTeamId": "189",
      "completed": true,
      "status": "Final",
      "homeScore": 77,
      "awayScore": 65,
      "actualSpread": -12,
      "winner": "HOME"
    },
    {
      "espnEventId": "401851442",
      "commence_time": "2026-03-05T00:00Z",
      "home_team": "Purdue Fort Wayne Mastodons",
      "away_team": "Robert Morris Colonials",
      "home_espnTeamId": "2870",
      "away_espnTeamId": "2523",
      "completed": true,
      "status": "Final",
      "homeScore": 73,
      "awayScore": 43,
      "actualSpread": -30,
      "winner": "HOME"
    },
    {
      "espnEventId": "401851441",
      "commence_time": "2026-03-05T00:00Z",
      "home_team": "Northern Kentucky Norse",
      "away_team": "IU Indianapolis Jaguars",
      "home_espnTeamId": "94",
      "away_espnTeamId": "85",
      "completed": true,
      "status": "Final",
      "homeScore": 72,
      "awayScore": 74,
      "actualSpread": 2,
      "winner": "AWAY"
    },
    {
      "espnEventId": "401851440",
      "commence_time": "2026-03-05T00:00Z",
      "home_team": "Cleveland State Vikings",
      "away_team": "Oakland Golden Grizzlies",
      "home_espnTeamId": "325",
      "away_espnTeamId": "2473",
      "completed": true,
      "status": "Final",
      "homeScore": 81,
      "awayScore": 80,
      "actualSpread": -1,
      "winner": "HOME"
    },
    {
      "espnEventId": "401851439",
      "commence_time": "2026-03-05T00:00Z",
      "home_team": "Youngstown State Penguins",
      "away_team": "Wright State Raiders",
      "home_espnTeamId": "2754",
      "away_espnTeamId": "2750",
      "completed": true,
      "status": "Final",
      "homeScore": 76,
      "awayScore": 60,
      "actualSpread": -16,
      "winner": "HOME"
    },
    {
      "espnEventId": "401823083",
      "commence_time": "2026-03-05T00:00Z",
      "home_team": "Navy Midshipmen",
      "away_team": "Loyola Maryland Greyhounds",
      "home_espnTeamId": "2426",
      "away_espnTeamId": "2352",
      "completed": true,
      "status": "Final",
      "homeScore": 72,
      "awayScore": 50,
      "actualSpread": -22,
      "winner": "HOME"
    },
    {
      "espnEventId": "401814682",
      "commence_time": "2026-03-05T00:00Z",
      "home_team": "Miami (OH) RedHawks",
      "away_team": "Kent State Golden Flashes",
      "home_espnTeamId": "193",
      "away_espnTeamId": "2309",
      "completed": true,
      "status": "Final",
      "homeScore": 71,
      "awayScore": 52,
      "actualSpread": -19,
      "winner": "HOME"
    },
    {
      "espnEventId": "401814680",
      "commence_time": "2026-03-05T00:00Z",
      "home_team": "Northern Illinois Huskies",
      "away_team": "Buffalo Bulls",
      "home_espnTeamId": "2459",
      "away_espnTeamId": "2084",
      "completed": true,
      "status": "Final",
      "homeScore": 56,
      "awayScore": 53,
      "actualSpread": -3,
      "winner": "HOME"
    },
    {
      "espnEventId": "401813245",
      "commence_time": "2026-03-05T00:00Z",
      "home_team": "Western Michigan Broncos",
      "away_team": "Toledo Rockets",
      "home_espnTeamId": "2711",
      "away_espnTeamId": "2649",
      "completed": true,
      "status": "Final",
      "homeScore": 49,
      "awayScore": 56,
      "actualSpread": 7,
      "winner": "AWAY"
    },
    {
      "espnEventId": "401828143",
      "commence_time": "2026-03-05T00:30Z",
      "home_team": "UTSA Roadrunners",
      "away_team": "Tulsa Golden Hurricane",
      "home_espnTeamId": "2636",
      "away_espnTeamId": "202",
      "completed": true,
      "status": "Final",
      "homeScore": 41,
      "awayScore": 53,
      "actualSpread": 12,
      "winner": "AWAY"
    },
    {
      "espnEventId": "401851443",
      "commence_time": "2026-03-05T01:00Z",
      "home_team": "Green Bay Phoenix",
      "away_team": "Detroit Mercy Titans",
      "home_espnTeamId": "2739",
      "away_espnTeamId": "2174",
      "completed": true,
      "status": "Final",
      "homeScore": 81,
      "awayScore": 57,
      "actualSpread": -24,
      "winner": "HOME"
    },
    {
      "espnEventId": "401828142",
      "commence_time": "2026-03-05T01:00Z",
      "home_team": "Memphis Tigers",
      "away_team": "UAB Blazers",
      "home_espnTeamId": "235",
      "away_espnTeamId": "5",
      "completed": true,
      "status": "Final",
      "homeScore": 76,
      "awayScore": 79,
      "actualSpread": 3,
      "winner": "AWAY"
    },
    {
      "espnEventId": "401851600",
      "commence_time": "2026-03-05T01:30Z",
      "home_team": "Alabama Crimson Tide",
      "away_team": "Missouri Tigers",
      "home_espnTeamId": "333",
      "away_espnTeamId": "142",
      "completed": true,
      "status": "Final",
      "homeScore": 65,
      "awayScore": 48,
      "actualSpread": -17,
      "winner": "HOME"
    },
    {
      "espnEventId": "401851368",
      "commence_time": "2026-03-05T01:30Z",
      "home_team": "Oregon Ducks",
      "away_team": "Purdue Boilermakers",
      "home_espnTeamId": "2483",
      "away_espnTeamId": "2509",
      "completed": true,
      "status": "Final",
      "homeScore": 82,
      "awayScore": 64,
      "actualSpread": -18,
      "winner": "HOME"
    },
    {
      "espnEventId": "401851281",
      "commence_time": "2026-03-05T02:17Z",
      "home_team": "Kansas Jayhawks",
      "away_team": "UCF Knights",
      "home_espnTeamId": "2305",
      "away_espnTeamId": "2116",
      "completed": true,
      "status": "Final",
      "homeScore": 56,
      "awayScore": 35,
      "actualSpread": -21,
      "winner": "HOME"
    },
    {
      "espnEventId": "401831338",
      "commence_time": "2026-03-05T02:30Z",
      "home_team": "UNLV Lady Rebels",
      "away_team": "Boise State Broncos",
      "home_espnTeamId": "2439",
      "away_espnTeamId": "68",
      "completed": true,
      "status": "Final",
      "homeScore": 76,
      "awayScore": 47,
      "actualSpread": -29,
      "winner": "HOME"
    }
  ]
}
